tabular_transformer/__init__.py
tabular_transformer/data_common.py
tabular_transformer/datareader.py
tabular_transformer/featurestats.py
tabular_transformer/hyperparameters.py
tabular_transformer/losses.py
tabular_transformer/metrics.py
tabular_transformer/predictor.py
tabular_transformer/tabular_dataset.py
tabular_transformer/tabular_loader.py
tabular_transformer/tabular_transformer.py
tabular_transformer/trainer.py
tabular_transformer/util.py
tabular_transformer-0.3.0.dist-info/LICENSE
tabular_transformer-0.3.0.dist-info/METADATA
tabular_transformer-0.3.0.dist-info/WHEEL
tabular_transformer-0.3.0.dist-info/top_level.txt
tabular_transformer-0.3.0.dist-info/RECORD
